bank_xgb/__init__.py
bank_xgb/bankXGB.py
XGB_for_bank_marketing-1.0.8.dist-info/LICENSE.txt
XGB_for_bank_marketing-1.0.8.dist-info/METADATA
XGB_for_bank_marketing-1.0.8.dist-info/WHEEL
XGB_for_bank_marketing-1.0.8.dist-info/top_level.txt
XGB_for_bank_marketing-1.0.8.dist-info/RECORD
